LICENSE.md
MANIFEST.in
README.md
setup.py
hass_frontend/1787f82dbc6f628cef0e.chunk.js
hass_frontend/1787f82dbc6f628cef0e.chunk.js.LICENSE
hass_frontend/1787f82dbc6f628cef0e.chunk.js.gz
hass_frontend/1787f82dbc6f628cef0e.chunk.js.map
hass_frontend/1c429ce70d5b6e463a9f.chunk.js
hass_frontend/1c429ce70d5b6e463a9f.chunk.js.gz
hass_frontend/1c429ce70d5b6e463a9f.chunk.js.map
hass_frontend/3149d05bc0903ae92897.chunk.js
hass_frontend/3149d05bc0903ae92897.chunk.js.LICENSE
hass_frontend/3149d05bc0903ae92897.chunk.js.gz
hass_frontend/3149d05bc0903ae92897.chunk.js.map
hass_frontend/32a930f523b871e02e26.chunk.js
hass_frontend/32a930f523b871e02e26.chunk.js.LICENSE
hass_frontend/32a930f523b871e02e26.chunk.js.gz
hass_frontend/32a930f523b871e02e26.chunk.js.map
hass_frontend/3a1f4fc72884abbc027b.chunk.js
hass_frontend/3a1f4fc72884abbc027b.chunk.js.LICENSE
hass_frontend/3a1f4fc72884abbc027b.chunk.js.gz
hass_frontend/3a1f4fc72884abbc027b.chunk.js.map
hass_frontend/3efa5bcea707d84ab8fb.chunk.js
hass_frontend/3efa5bcea707d84ab8fb.chunk.js.LICENSE
hass_frontend/3efa5bcea707d84ab8fb.chunk.js.gz
hass_frontend/3efa5bcea707d84ab8fb.chunk.js.map
hass_frontend/41843ddd1652a9a26497.chunk.js
hass_frontend/41843ddd1652a9a26497.chunk.js.LICENSE
hass_frontend/41843ddd1652a9a26497.chunk.js.gz
hass_frontend/41843ddd1652a9a26497.chunk.js.map
hass_frontend/4ebb0219caf9f4a95b4c.chunk.js
hass_frontend/4ebb0219caf9f4a95b4c.chunk.js.LICENSE
hass_frontend/4ebb0219caf9f4a95b4c.chunk.js.gz
hass_frontend/4ebb0219caf9f4a95b4c.chunk.js.map
hass_frontend/62b688ef1a853af1998e.chunk.js
hass_frontend/62b688ef1a853af1998e.chunk.js.gz
hass_frontend/62b688ef1a853af1998e.chunk.js.map
hass_frontend/6c9819f56b370e29b295.chunk.js
hass_frontend/6c9819f56b370e29b295.chunk.js.LICENSE
hass_frontend/6c9819f56b370e29b295.chunk.js.gz
hass_frontend/6c9819f56b370e29b295.chunk.js.map
hass_frontend/720efab2bcd7c9c5b9ef.chunk.js
hass_frontend/720efab2bcd7c9c5b9ef.chunk.js.gz
hass_frontend/720efab2bcd7c9c5b9ef.chunk.js.map
shimao_hass_frontend.egg-info/PKG-INFO
shimao_hass_frontend.egg-info/SOURCES.txt
shimao_hass_frontend.egg-info/dependency_links.txt
shimao_hass_frontend.egg-info/not-zip-safe
shimao_hass_frontend.egg-info/requires.txt
shimao_hass_frontend.egg-info/top_level.txt