Metadata-Version: 1.0
Name: shimao-hass-frontend
Version: 20180609
Summary: shimao hass frontend
Home-page: https://github.com/home-assistant/home-assistant-polymer
Author: The Home Assistant Authors
Author-email: hello@home-assistant.io
License: Apache License 2.0
Platform: UNKNOWN
